tests/test_client.py
tests/test_integration.py
tests/test_utils.py
zoektpy/__init__.py
zoektpy/cli.py
zoektpy/client.py
zoektpy/exceptions.py
zoektpy/models.py
zoektpy/utils.py
zoektpy-0.2.0.dist-info/licenses/LICENSE
zoektpy-0.2.0.dist-info/METADATA
zoektpy-0.2.0.dist-info/WHEEL
zoektpy-0.2.0.dist-info/entry_points.txt
zoektpy-0.2.0.dist-info/top_level.txt
zoektpy-0.2.0.dist-info/RECORD
