Metadata-Version: 2.4
Name: zoektpy
Version: 0.2.0
Summary: Python client library for Zoekt code search
Author-email: Udbhav Agarwal <udbhav44@gmail.com>
Project-URL: Homepage, https://github.com/udbhav-44/zoekt-py
Project-URL: Bug Tracker, https://github.com/udbhav-44/zoekt-py/issues
Classifier: Development Status :: 3 - Alpha
Classifier: Intended Audience :: Developers
Classifier: Topic :: Software Development :: Libraries
Classifier: Programming Language :: Python :: 3
Classifier: Programming Language :: Python :: 3.10
Classifier: Programming Language :: Python :: 3.11
Classifier: License :: OSI Approved :: MIT License
Classifier: Operating System :: OS Independent
Requires-Python: >=3.10
License-File: LICENSE
Requires-Dist: requests>=2.32.3
Requires-Dist: click>=8.1.8
Requires-Dist: pydantic>=2.11.7
Requires-Dist: rich>=13.9.4
Requires-Dist: aiohttp>=3.10.11
Provides-Extra: dev
Requires-Dist: pytest>=6.0.0; extra == "dev"
Requires-Dist: black>=21.5b2; extra == "dev"
Requires-Dist: mypy>=0.812; extra == "dev"
Requires-Dist: isort>=5.8.0; extra == "dev"
Requires-Dist: flake8>=3.9.1; extra == "dev"
Requires-Dist: responses>=0.25.8; extra == "dev"
Dynamic: license-file
